llm_consortium/__init__.py
llm_consortium/arbiter_prompt.xml
llm_consortium/iteration_prompt.txt
llm_consortium/protocol.py
llm_consortium/system_prompt.txt
llm_consortium-0.3.dist-info/METADATA
llm_consortium-0.3.dist-info/WHEEL
llm_consortium-0.3.dist-info/entry_points.txt
llm_consortium-0.3.dist-info/top_level.txt
llm_consortium-0.3.dist-info/RECORD
