Metadata-Version: 2.2
Name: llm-consortium
Version: 0.3
Summary: LLM plugin implementing Andrej Karpathy's model consortium tweet
Author-email: Thomas Hughes <irthomasthomas@gmail.com>
License: Apache-2.0
Project-URL: Homepage, https://github.com/irthomasthomas/karpathy-consortium
Project-URL: Changelog, https://github.com/irthomasthomas/karpathy-consortium/releases
Project-URL: Issues, https://github.com/irthomasthomas/karpathy-consortium/issues
Classifier: License :: OSI Approved :: Apache Software License
Requires-Dist: llm
Requires-Dist: click
Requires-Dist: httpx
Requires-Dist: sqlite-utils
Requires-Dist: asyncio
